Metadata-Version: 2.1
Name: gpscript
Version: 1.1.9
Summary: A package manager to install general purpose script by Google Developer Student Club
Home-page: UNKNOWN
Author: Ujjwal Kar
Author-email: ujjwalkar21@gmail.com
License: UNKNOWN
Keywords: python
Platform: UNKNOWN
Classifier: Development Status :: 1 - Planning
Classifier: Intended Audience :: Developers
Classifier: Programming Language :: Python :: 3
Classifier: Operating System :: Unix
Classifier: Operating System :: MacOS :: MacOS X
Classifier: Operating System :: Microsoft :: Windows
License-File: LICENSE
